rcoc/__init__.py
rcoc/cities.csv
rcoc/rcoc.py
rcoc-1.1.16.dist-info/LICENSE
rcoc-1.1.16.dist-info/METADATA
rcoc-1.1.16.dist-info/WHEEL
rcoc-1.1.16.dist-info/top_level.txt
rcoc-1.1.16.dist-info/RECORD
