Metadata-Version: 2.1
Name: rcoc
Version: 1.1.16
Summary: RCOC - Random Country Or City name generator
Home-page: https://github.com/touhf/rcoc
Download-URL: https://github.com/touhf/rcoc/archive/refs/tags/1.1.16.tar.gz
Author: touhf
Author-email: tobytubar@gmail.com
License: MIT
Keywords: country,city,generator
Classifier: Development Status :: 5 - Production/Stable
Classifier: Intended Audience :: Developers
Classifier: Topic :: Software Development :: Build Tools
Classifier: License :: OSI Approved :: MIT License
Classifier: Programming Language :: Python :: 3
License-File: LICENSE
